infograph/__init__.py
infograph/charts/AbstractChart.py
infograph/charts/BarChart.py
infograph/charts/GeoMap.py
infograph/charts/GeoMapDorling.py
infograph/charts/PieChart.py
infograph/charts/RangeBarChart.py
infograph/charts/TreeMap.py
infograph/charts/__init__.py
infograph/core/DEFAULT.py
infograph/core/DataColor.py
infograph/core/DataTable.py
infograph/core/Infograph.py
infograph/core/Plt.py
infograph/core/__init__.py
infograph/math/Bounds.py
infograph/math/Dorling.py
infograph/math/Ellipse.py
infograph/math/__init__.py
infograph_nuuuwan-1.0.4.dist-info/LICENSE
infograph_nuuuwan-1.0.4.dist-info/METADATA
infograph_nuuuwan-1.0.4.dist-info/WHEEL
infograph_nuuuwan-1.0.4.dist-info/top_level.txt
infograph_nuuuwan-1.0.4.dist-info/RECORD
